leaf_pymavlink-0.1.14.dist-info/RECORD
leaf_pymavlink-0.1.14.dist-info/WHEEL
leaf_pymavlink-0.1.14.dist-info/top_level.txt
leaf_pymavlink-0.1.14.dist-info/METADATA
leaf_pymavlink-0.1.14.dist-info/licenses/COPYING
leaf_pymavlink-0.1.14.data/scripts/mavplayback.py
leaf_pymavlink-0.1.14.data/scripts/mavfft_isb.py
leaf_pymavlink-0.1.14.data/scripts/mavfft.py
leaf_pymavlink-0.1.14.data/scripts/magfit_motors.py
leaf_pymavlink-0.1.14.data/scripts/magfit_delta.py
leaf_pymavlink-0.1.14.data/scripts/magfit_gps.py
leaf_pymavlink-0.1.14.data/scripts/mavsigloss.py
leaf_pymavlink-0.1.14.data/scripts/mavlink_bitmask_decoder.py
leaf_pymavlink-0.1.14.data/scripts/magfit.py
leaf_pymavlink-0.1.14.data/scripts/mavflightmodes.py
leaf_pymavlink-0.1.14.data/scripts/mavgpslock.py
leaf_pymavlink-0.1.14.data/scripts/mavsearch.py
leaf_pymavlink-0.1.14.data/scripts/mavextract.py
leaf_pymavlink-0.1.14.data/scripts/mavsummarize.py
leaf_pymavlink-0.1.14.data/scripts/mavflighttime.py
leaf_pymavlink-0.1.14.data/scripts/mavgen.py
leaf_pymavlink-0.1.14.data/scripts/mavkml.py
leaf_pymavlink-0.1.14.data/scripts/mavmission.py
leaf_pymavlink-0.1.14.data/scripts/mavtogpx.py
leaf_pymavlink-0.1.14.data/scripts/magfit_WMM.py
leaf_pymavlink-0.1.14.data/scripts/mavtomfile.py
leaf_pymavlink-0.1.14.data/scripts/mavparmdiff.py
leaf_pymavlink-0.1.14.data/scripts/mavlogdump.py
leaf_pymavlink-0.1.14.data/scripts/mavparms.py
leaf_pymavlink-0.1.14.data/scripts/mavgraph.py
leaf_pymavlink-0.1.14.data/scripts/mavloss.py
pymavlink/mavtestgen.py
pymavlink/CSVReader.py
pymavlink/mavwp.py
pymavlink/mavutil.py
pymavlink/mavftpfs.py
pymavlink/quaternion.py
pymavlink/mavftp.py
pymavlink/__init__.py
pymavlink/fgFDM.py
pymavlink/rotmat.py
pymavlink/DFReader.py
pymavlink/mavftp_op.py
pymavlink/mavparm.py
pymavlink/setup.py
pymavlink/mavextra.py
pymavlink/mavexpression.py
pymavlink/message_definitions/v1.0/python_array_test.xml
pymavlink/message_definitions/v1.0/paparazzi.xml
pymavlink/message_definitions/v1.0/AVSSUAS.xml
pymavlink/message_definitions/v1.0/ardupilotmega.xml
pymavlink/message_definitions/v1.0/marsh.xml
pymavlink/message_definitions/v1.0/standard.xml
